bk_sales/__init__.py
bk_sales/bk_main.py
bk_sales/bk_prices.py
bk_sales-1.0.4.dist-info/METADATA
bk_sales-1.0.4.dist-info/WHEEL
bk_sales-1.0.4.dist-info/entry_points.txt
bk_sales-1.0.4.dist-info/top_level.txt
bk_sales-1.0.4.dist-info/RECORD
